ads_log_daemon/__init__.py
ads_log_daemon/_version.py
ads_log_daemon/tests/__init__.py
ads_log_daemon/tests/conftest.py
ads_log_daemon/tests/test_blank.py
ads_log_daemon-0.0.1.dist-info/AUTHORS.rst
ads_log_daemon-0.0.1.dist-info/LICENSE
ads_log_daemon-0.0.1.dist-info/METADATA
ads_log_daemon-0.0.1.dist-info/WHEEL
ads_log_daemon-0.0.1.dist-info/entry_points.txt
ads_log_daemon-0.0.1.dist-info/top_level.txt
ads_log_daemon-0.0.1.dist-info/RECORD
