Metadata-Version: 2.1
Name: ads-log-daemon
Version: 0.0.1
Summary: Daemon for translating TwinCAT ADS Logger messages to JSON for interpretation by logstash.
Home-page: https://github.com/pcdshub/ads-log-daemon
Author: SLAC National Accelerator Laboratory
Author-email: UNKNOWN
License: BSD
Platform: UNKNOWN
Classifier: Development Status :: 2 - Pre-Alpha
Classifier: Natural Language :: English
Classifier: Programming Language :: Python :: 3
Requires-Dist: versioneer
Requires-Dist: ads-async
